<?xml version="1.0" encoding="utf-8" ?>
<dwsync>
<file name="index.ctp" server="10.0.0.10//var/www/youandi/" local="130244104039424726" remote="130390298030000000" Dst="1" />
<file name="send.ctp" server="10.0.0.10//var/www/youandi/" local="130244104019370053" remote="130390298030000000" Dst="1" />
<file name="send_confirm.ctp" server="10.0.0.10//var/www/youandi/" local="130244103993759881" remote="130390298030000000" Dst="1" />
<file name="send_reply.ctp" server="10.0.0.10//var/www/youandi/" local="130244103972223380" remote="130390298030000000" Dst="1" />
<file name="send_reply_confirm.ctp" server="10.0.0.10//var/www/youandi/" local="130244103953321518" remote="130390298030000000" Dst="1" />
<file name="send_to_user.ctp" server="10.0.0.10//var/www/youandi/" local="130244103933930751" remote="130390298040000000" Dst="1" />
<file name="send_to_user_confirm.ctp" server="10.0.0.10//var/www/youandi/" local="130244103915799990" remote="130390298040000000" Dst="1" />
<file name="view.ctp" server="10.0.0.10//var/www/youandi/" local="130244103897109751" remote="130390298040000000" Dst="1" />
</dwsync>